inbound/__init__.py
inbound/admin.py
inbound/apps.py
inbound/middleware.py
inbound/models.py
inbound/queries.py
inbound/services.py
inbound/tests.py
inbound/views.py
inbound/__pycache__/__init__.cpython-37.pyc
inbound/__pycache__/admin.cpython-37.pyc
inbound/__pycache__/middleware.cpython-37.pyc
inbound/__pycache__/models.cpython-37.pyc
inbound/__pycache__/queries.cpython-37.pyc
inbound/__pycache__/services.cpython-37.pyc
inbound/migrations/0001_initial.py
inbound/migrations/__init__.py
inbound/migrations/__pycache__/0001_initial.cpython-37.pyc
inbound/migrations/__pycache__/__init__.cpython-37.pyc
django_inbound_rules-1.1.0.dist-info/LICENSE
django_inbound_rules-1.1.0.dist-info/METADATA
django_inbound_rules-1.1.0.dist-info/WHEEL
django_inbound_rules-1.1.0.dist-info/top_level.txt
django_inbound_rules-1.1.0.dist-info/RECORD
