Metadata-Version: 2.1
Name: django-inbound-rules
Version: 1.1.0
Summary: Django Inbound Rules is an app to allow or restrict group of users on specified url(s) based on CIDR blocks(now IPv4 only) excluding user with superuser permissions.
Home-page: https://github.com/nilesh-kr-dubey/django-inbound-rules
Author: Nilesh Kumar Dubey
Author-email: nileshdubeyindia@gmail.com
License: MIT
Project-URL: Documentation, https://github.com/nilesh-kr-dubey/django-inbound-rules/tree/master/docs
Platform: UNKNOWN
Classifier: Environment :: Web Environment
Classifier: Framework :: Django
Classifier: Framework :: Django :: 2.0
Classifier: Framework :: Django :: 3.0
Classifier: Intended Audience :: Developers
Classifier: License :: OSI Approved :: MIT License
Classifier: Programming Language :: Python :: 3.6
Classifier: Programming Language :: Python :: 3.7
Classifier: Programming Language :: Python :: 3.8
Classifier: Topic :: Internet :: WWW/HTTP
Classifier: Topic :: Internet :: WWW/HTTP :: Dynamic Content
Requires-Dist: Django (>=2.0)
